.coverage
.gitignore
LICENSE
README.md
requirements.txt
setup.cfg
setup.py
.github/workflows/CI.yml
.github/workflows/publish.yml
archive/della_gatta_gene.csv
archive/heinonen_4.csv
archive/jump1d.csv
archive/motorcycle_helmet.csv
archive/olympic_men100m.csv
figures/DellaGattaGene.jpg
figures/Heinonen4.jpg
figures/Jump1D.jpg
figures/MotorcycleHelmet.jpg
figures/NonStat2D.jpg
figures/Olympic.jpg
figures/SineJump1D.jpg
figures/SineNoisy.jpg
figures/Smooth1D.jpg
figures/Step.jpg
notebooks/visualize.ipynb
regdata/__init__.py
regdata/config.py
regdata.egg-info/PKG-INFO
regdata.egg-info/SOURCES.txt
regdata.egg-info/dependency_links.txt
regdata.egg-info/requires.txt
regdata.egg-info/top_level.txt
regdata/dataloaders/__init__.py
regdata/dataloaders/base.py
regdata/dataloaders/della_gatta_gene.py
regdata/dataloaders/heinonen_4.py
regdata/dataloaders/jump1d.py
regdata/dataloaders/mcycle.py
regdata/dataloaders/noisy_sine.py
regdata/dataloaders/nonstat2d.py
regdata/dataloaders/olympic.py
regdata/dataloaders/sinejump.py
regdata/dataloaders/smooth1d.py
regdata/dataloaders/step.py
retrive_info/data_download.md
tests/__init__.py
tests/common.py
tests/lib.py
tests/test_all.py
tests/test_backend.py
tests/test_noise.py
tests/test_plotting.py
tests/test_scaler.py