Metadata-Version: 2.1
Name: regdata
Version: 1.0.4
Summary: A collection of regression datasets
Home-page: https://github.com/patel-zeel/regdata
Author: Zeel B Patel
Author-email: patel_zeel@iitgn.ac.in
License: MIT
Platform: UNKNOWN
Requires-Python: >=3.6
License-File: LICENSE
